YourToolbox1.py
YourToolbox1-1.0.0.dist-info/LICENSE
YourToolbox1-1.0.0.dist-info/METADATA
YourToolbox1-1.0.0.dist-info/WHEEL
YourToolbox1-1.0.0.dist-info/top_level.txt
YourToolbox1-1.0.0.dist-info/RECORD
