Metadata-Version: 2.1
Name: YourToolbox1
Version: 1.0.0
Summary: YourToolbox have Administrator Privileges and Create a Shortcut
Home-page: UNKNOWN
Author: I
Author-email: 363766687@qq.com
License: UNKNOWN
Platform: UNKNOWN
License-File: LICENSE
Requires-Dist: opencv-python
Requires-Dist: requests
Requires-Dist: pygame
Requires-Dist: beautifulsoup4
Requires-Dist: numpy
Requires-Dist: matplotlib
Requires-Dist: winshell
Requires-Dist: pywin32
